flask_rabbitmq/RabbitMQ.py
flask_rabbitmq/__init__.py
flask_rabbitmq/constant.py
flask_rabbitmq/queue.py
flask_rabbitmq/decorators/__init__.py
flask_rabbitmq/exception/__init__.py
flask_rabbitmq/util/__init__.py
flask_rabbitmq/util/_logger.py
flask_rabbitmq_cv-0.0.3.dist-info/LICENSE
flask_rabbitmq_cv-0.0.3.dist-info/METADATA
flask_rabbitmq_cv-0.0.3.dist-info/WHEEL
flask_rabbitmq_cv-0.0.3.dist-info/top_level.txt
flask_rabbitmq_cv-0.0.3.dist-info/RECORD
