Metadata-Version: 2.1
Name: flask-rabbitmq-cv
Version: 0.0.3
Summary: Let rabbitmq use flask development more easy! ! !
Home-page: https://github.com/claudiuvintila/flask-rabbitmq
Author: Pushy
Author-email: claudiu.vintila@gmail.com
License: UNKNOWN
Platform: UNKNOWN
Requires-Dist: pika
